helper/__init__.py
helper/configLoader.py
helper/preparationProcess.py
helper/scraping.py
helper/trainingProcess.py
miping/.env.example
miping/__init__.py
miping/one_time_setup.py
miping/application/__init__.py
miping/application/modelApplication.py
miping/application/predictionErrors.py
miping/interfaces/__init__.py
miping/interfaces/glove.py
miping/interfaces/helper.py
miping/interfaces/ibm.py
miping/interfaces/liwc.py
miping/interfaces/maps.py
miping/interfaces/twitter.py
miping/models/__init__.py
miping/models/bayesianRidge.py
miping/models/decisionTree.py
miping/models/gaussianProcessRegressor.py
miping/models/modelBase.py
miping/models/onnxModel.py
miping/models/profile.py
miping/models/profileCollection.py
miping/models/randomForest.py
miping/models/ridgeRegression.py
miping/models/supportVectorMachine.py
miping/models/tweetCollection.py
miping/models/tweetObj.py
miping/models/user.py
miping/models/userCollection.py
miping/trainedModels/__init__.py
miping/trainedModels/glovebig5_agreeableness.ONNX
miping/trainedModels/glovebig5_conscientiousness.ONNX
miping/trainedModels/glovebig5_extraversion.ONNX
miping/trainedModels/glovebig5_neuroticism.ONNX
miping/trainedModels/glovebig5_openness.ONNX
miping/trainedModels/trainedModels.py
miping/training/__init__.py
miping/training/dataPreparation.py
miping/training/features.py
miping/training/modelTraining.py
miping/training/noGloveValueError.py
miping/webapp/__init__.py
miping/webapp/invalidUsage.py
miping/webapp/requestHandler.py
miping/webapp/webapplication.py
miping/webapp/wsgi.py
miping/webapp/webfiles/miping-gunicorn.conf
miping/webapp/webfiles/start_webserver.sh
miping/webapp/webfiles/stop_webserver.sh
miping/webapp/webfiles/sites-available/localhost.txt
miping/webapp/webfiles/sites-available/localnetwork.txt
miping/webapp/webfiles/sites-available/miping.txt
miping/webapp/webfiles/www/index.html
miping/webapp/webfiles/www/css/normalize.css
miping/webapp/webfiles/www/css/skeleton.css
miping-0.2.0.dist-info/LICENSE
miping-0.2.0.dist-info/METADATA
miping-0.2.0.dist-info/WHEEL
miping-0.2.0.dist-info/top_level.txt
miping-0.2.0.dist-info/RECORD
